{"2750272":{"to":8,"transport":1,"price":181,"duration":480},"2750367":{"to":9,"transport":1,"price":181,"duration":595},"2750055":{"to":11,"transport":1,"price":416,"duration":1095},"2750312":{"to":13,"transport":1,"price":317,"duration":590},"2750283":{"to":14,"transport":1,"price":358,"duration":1130},"2750219":{"to":15,"transport":1,"price":335,"duration":690},"2750224":{"to":16,"transport":1,"price":295,"duration":1270},"2750127":{"to":17,"transport":1,"price":63,"duration":465},"2750359":{"to":18,"transport":1,"price":280,"duration":820},"2750160":{"to":20,"transport":1,"price":226,"duration":755},"2750271":{"to":21,"transport":1,"price":226,"duration":600},"2750227":{"to":22,"transport":1,"price":229,"duration":475},"2750018":{"to":23,"transport":1,"price":298,"duration":845},"2750364":{"to":24,"transport":1,"price":281,"duration":900},"2750398":{"to":25,"transport":1,"price":147,"duration":655},"2750099":{"to":26,"transport":1,"price":226,"duration":375},"2750320":{"to":27,"transport":1,"price":389,"duration":1080},"2750101":{"to":28,"transport":1,"price":135,"duration":585},"2750059":{"to":29,"transport":1,"price":154,"duration":715},"2750097":{"to":30,"transport":1,"price":389,"duration":640},"2750116":{"to":31,"transport":1,"price":41,"duration":475},"2750226":{"to":32,"transport":1,"price":205,"duration":555},"2750100":{"to":33,"transport":1,"price":172,"duration":460},"2750021":{"to":34,"transport":1,"price":54,"duration":565},"2750188":{"to":35,"transport":1,"price":127,"duration":340},"2750123":{"to":36,"transport":1,"price":452,"duration":1329},"2750406":{"to":37,"transport":1,"price":295,"duration":910},"2750257":{"to":38,"transport":1,"price":289,"duration":825},"2750202":{"to":39,"transport":1,"price":298,"duration":950},"2750231":{"to":40,"transport":1,"price":344,"duration":865},"2750258":{"to":41,"transport":1,"price":362,"duration":743},"2750336":{"to":42,"transport":1,"price":244,"duration":660},"2750394":{"to":43,"transport":1,"price":324,"duration":840},"2750402":{"to":44,"transport":1,"price":59,"duration":575},"2750140":{"to":45,"transport":1,"price":58,"duration":520},"2750411":{"to":48,"transport":1,"price":438,"duration":1185},"2750387":{"to":51,"transport":1,"price":405,"duration":1165},"2750024":{"to":53,"transport":1,"price":302,"duration":1320},"2750369":{"to":55,"transport":1,"price":265,"duration":845},"2750141":{"to":56,"transport":1,"price":199,"duration":895},"2750095":{"to":57,"transport":1,"price":254,"duration":880},"2750296":{"to":58,"transport":1,"price":145,"duration":450},"2750212":{"to":59,"transport":1,"price":354,"duration":720},"2750042":{"to":60,"transport":1,"price":656,"duration":990},"2750036":{"to":61,"transport":1,"price":393,"duration":1075},"2750232":{"to":62,"transport":1,"price":261,"duration":790},"2750301":{"to":63,"transport":1,"price":274,"duration":715},"2750091":{"to":64,"transport":1,"price":467,"duration":1010},"2750363":{"to":65,"transport":1,"price":329,"duration":1135},"2750096":{"to":66,"transport":1,"price":221,"duration":820},"2750345":{"to":67,"transport":1,"price":501,"duration":995},"2750150":{"to":68,"transport":1,"price":407,"duration":1095},"2750107":{"to":69,"transport":1,"price":81,"duration":435},"2750342":{"to":70,"transport":1,"price":558,"duration":1610},"2750333":{"to":71,"transport":1,"price":358,"duration":1160},"2750304":{"to":72,"transport":1,"price":667,"duration":1510},"2750265":{"to":73,"transport":1,"price":515,"duration":2245},"2750230":{"to":74,"transport":1,"price":35,"duration":330},"2750382":{"to":75,"transport":1,"price":387,"duration":1115},"2750260":{"to":76,"transport":1,"price":363,"duration":1085},"2750108":{"to":77,"transport":1,"price":246,"duration":1045},"2750328":{"to":78,"transport":1,"price":97,"duration":310},"2750417":{"to":79,"transport":1,"price":407,"duration":1110},"2750371":{"to":80,"transport":1,"price":429,"duration":1120},"2750054":{"to":81,"transport":1,"price":298,"duration":1065},"2750032":{"to":82,"transport":1,"price":433,"duration":880},"2750072":{"to":83,"transport":1,"price":339,"duration":1185},"2750324":{"to":84,"transport":1,"price":111,"duration":520},"2750165":{"to":85,"transport":1,"price":323,"duration":980},"2750323":{"to":86,"transport":1,"price":60,"duration":480},"2750209":{"to":87,"transport":1,"price":335,"duration":915},"2750168":{"to":88,"transport":1,"price":501,"duration":1005},"2750390":{"to":89,"transport":1,"price":371,"duration":1070},"2750346":{"to":90,"transport":1,"price":343,"duration":970},"2750303":{"to":91,"transport":1,"price":184,"duration":765},"2750039":{"to":92,"transport":1,"price":1094,"duration":990},"2750193":{"to":93,"transport":1,"price":243,"duration":640},"2750218":{"to":94,"transport":1,"price":367,"duration":990},"2750106":{"to":95,"transport":1,"price":234,"duration":490},"2750122":{"to":96,"transport":1,"price":339,"duration":875},"2750166":{"to":97,"transport":1,"price":392,"duration":1070},"2750412":{"to":98,"transport":1,"price":264,"duration":1170},"2750374":{"to":99,"transport":1,"price":298,"duration":985},"2750026":{"to":101,"transport":1,"price":51,"duration":350},"2750358":{"to":103,"transport":1,"price":60,"duration":565},"2750037":{"to":104,"transport":1,"price":45,"duration":120},"2750305":{"to":105,"transport":1,"price":49,"duration":355},"2750322":{"to":106,"transport":1,"price":44,"duration":300},"2750222":{"to":107,"transport":1,"price":51,"duration":320},"2750262":{"to":108,"transport":1,"price":74,"duration":340},"2750311":{"to":109,"transport":1,"price":27,"duration":65},"2750125":{"to":111,"transport":1,"price":55,"duration":145},"2750186":{"to":112,"transport":1,"price":59,"duration":410},"2750419":{"to":113,"transport":1,"price":65,"duration":385},"2750063":{"to":114,"transport":1,"price":98,"duration":375},"2750124":{"to":116,"transport":1,"price":75,"duration":125},"2750084":{"to":119,"transport":1,"price":55,"duration":295},"2750200":{"to":120,"transport":1,"price":49,"duration":155},"2750170":{"to":121,"transport":1,"price":26,"duration":625},"2750111":{"to":122,"transport":1,"price":34,"duration":150},"2750217":{"to":123,"transport":1,"price":55,"duration":215},"2750214":{"to":124,"transport":1,"price":69,"duration":140},"2750064":{"to":126,"transport":1,"price":50,"duration":225},"2750316":{"to":127,"transport":1,"price":32,"duration":240},"2750126":{"to":128,"transport":1,"price":45,"duration":90},"2750139":{"to":129,"transport":1,"price":30,"duration":125},"2750288":{"to":130,"transport":1,"price":30,"duration":65},"2750254":{"to":131,"transport":1,"price":60,"duration":380},"2750334":{"to":132,"transport":1,"price":77,"duration":470},"2750043":{"to":134,"transport":1,"price":22,"duration":255},"2750356":{"to":135,"transport":1,"price":77,"duration":210},"2750235":{"to":136,"transport":1,"price":17,"duration":445},"2750229":{"to":137,"transport":1,"price":40,"duration":110},"2750234":{"to":140,"transport":1,"price":27,"duration":95},"2750112":{"to":142,"transport":1,"price":51,"duration":395},"2750422":{"to":145,"transport":1,"price":100,"duration":125},"2750098":{"to":146,"transport":1,"price":25,"duration":250},"2750132":{"to":147,"transport":1,"price":74,"duration":155},"2750172":{"to":150,"transport":1,"price":25,"duration":390},"2750208":{"to":151,"transport":8,"price":15,"duration":255},"2750003":{"to":151,"transport":2,"price":16,"duration":285},"2750264":{"to":151,"transport":3,"price":18,"duration":208},"2750418":{"to":152,"transport":1,"price":35,"duration":80},"2750329":{"to":153,"transport":1,"price":24,"duration":275},"2750354":{"to":154,"transport":1,"price":80,"duration":330},"2750177":{"to":159,"transport":1,"price":93,"duration":275},"2750379":{"to":160,"transport":1,"price":49,"duration":235},"2750174":{"to":161,"transport":1,"price":74,"duration":120},"2750086":{"to":162,"transport":1,"price":65,"duration":190},"2750088":{"to":163,"transport":1,"price":103,"duration":480},"2750309":{"to":164,"transport":1,"price":88,"duration":330},"2750027":{"to":166,"transport":1,"price":68,"duration":305},"2750004":{"to":171,"transport":1,"price":94,"duration":490},"2750143":{"to":172,"transport":1,"price":55,"duration":225},"2750178":{"to":174,"transport":1,"price":88,"duration":115},"2750161":{"to":176,"transport":1,"price":45,"duration":380},"2750287":{"to":177,"transport":1,"price":40,"duration":70},"2750253":{"to":178,"transport":1,"price":60,"duration":525},"2750307":{"to":179,"transport":1,"price":35,"duration":375},"2750183":{"to":180,"transport":1,"price":60,"duration":375},"2750192":{"to":181,"transport":1,"price":75,"duration":260},"2750190":{"to":183,"transport":1,"price":45,"duration":350},"2750201":{"to":184,"transport":1,"price":45,"duration":315},"2750250":{"to":186,"transport":1,"price":45,"duration":285},"2750341":{"to":189,"transport":1,"price":32,"duration":60},"2750010":{"to":189,"transport":10,"price":34,"duration":660},"2750044":{"to":191,"transport":1,"price":18,"duration":255},"2750137":{"to":192,"transport":1,"price":39,"duration":80},"2750196":{"to":193,"transport":1,"price":23,"duration":265},"2750129":{"to":194,"transport":1,"price":62,"duration":400},"2750365":{"to":196,"transport":1,"price":74,"duration":145},"2750175":{"to":197,"transport":1,"price":44,"duration":270},"2750405":{"to":200,"transport":1,"price":75,"duration":270},"2750372":{"to":201,"transport":1,"price":44,"duration":305},"2750028":{"to":203,"transport":1,"price":51,"duration":320},"2750413":{"to":204,"transport":1,"price":36,"duration":690},"2750280":{"to":205,"transport":1,"price":69,"duration":240},"2750089":{"to":206,"transport":1,"price":116,"duration":360},"2750420":{"to":207,"transport":1,"price":65,"duration":290},"2750360":{"to":213,"transport":1,"price":21,"duration":250},"2750326":{"to":214,"transport":1,"price":100,"duration":245},"2750216":{"to":215,"transport":1,"price":65,"duration":340},"2750350":{"to":218,"transport":1,"price":30,"duration":545},"2750181":{"to":219,"transport":1,"price":55,"duration":350},"2750198":{"to":222,"transport":1,"price":27,"duration":355},"2750076":{"to":224,"transport":1,"price":51,"duration":315},"2750400":{"to":225,"transport":1,"price":32,"duration":150},"2750162":{"to":227,"transport":1,"price":100,"duration":400},"2750047":{"to":228,"transport":1,"price":85,"duration":365},"2750131":{"to":230,"transport":1,"price":75,"duration":195},"2750353":{"to":231,"transport":1,"price":110,"duration":310},"2750274":{"to":233,"transport":1,"price":90,"duration":130},"2750308":{"to":235,"transport":1,"price":65,"duration":300},"2750318":{"to":237,"transport":1,"price":30,"duration":960},"2750366":{"to":239,"transport":1,"price":40,"duration":130},"2750133":{"to":240,"transport":1,"price":59,"duration":80},"2750090":{"to":242,"transport":1,"price":79,"duration":430},"2750197":{"to":243,"transport":1,"price":81,"duration":165},"2750176":{"to":246,"transport":1,"price":123,"duration":315},"2750092":{"to":247,"transport":1,"price":95,"duration":95},"2750157":{"to":248,"transport":1,"price":55,"duration":135},"2750035":{"to":249,"transport":1,"price":70,"duration":245},"2750056":{"to":250,"transport":1,"price":50,"duration":280},"2750136":{"to":252,"transport":1,"price":18,"duration":70},"2750247":{"to":253,"transport":1,"price":40,"duration":235},"2750087":{"to":257,"transport":1,"price":93,"duration":415},"2750286":{"to":260,"transport":1,"price":40,"duration":395},"2750053":{"to":261,"transport":1,"price":54,"duration":360},"2750020":{"to":263,"transport":1,"price":68,"duration":365},"2750128":{"to":264,"transport":1,"price":57,"duration":365},"2750278":{"to":265,"transport":1,"price":62,"duration":405},"2750182":{"to":266,"transport":1,"price":50,"duration":255},"2750331":{"to":267,"transport":1,"price":24,"duration":60},"2750256":{"to":268,"transport":1,"price":136,"duration":515},"2750102":{"to":269,"transport":1,"price":65,"duration":125},"2750058":{"to":270,"transport":1,"price":35,"duration":55},"2750205":{"to":274,"transport":1,"price":32,"duration":280},"2750069":{"to":277,"transport":1,"price":52,"duration":195},"2750362":{"to":279,"transport":1,"price":51,"duration":405},"2750082":{"to":282,"transport":1,"price":110,"duration":255},"2750203":{"to":284,"transport":1,"price":50,"duration":185},"2750189":{"to":285,"transport":1,"price":35,"duration":70},"2750156":{"to":286,"transport":1,"price":21,"duration":235},"2750290":{"to":287,"transport":1,"price":35,"duration":55},"2750121":{"to":288,"transport":1,"price":79,"duration":555},"2750048":{"to":289,"transport":1,"price":77,"duration":509},"2750300":{"to":290,"transport":1,"price":35,"duration":540},"2750244":{"to":291,"transport":1,"price":50,"duration":270},"2750191":{"to":293,"transport":1,"price":36,"duration":110},"2750343":{"to":295,"transport":1,"price":23,"duration":345},"2750378":{"to":297,"transport":1,"price":64,"duration":125},"2750138":{"to":299,"transport":1,"price":30,"duration":360},"2750215":{"to":300,"transport":1,"price":72,"duration":385},"2750414":{"to":302,"transport":1,"price":131,"duration":375},"2750310":{"to":303,"transport":1,"price":30,"duration":55},"2750373":{"to":305,"transport":1,"price":61,"duration":190},"2750194":{"to":307,"transport":1,"price":86,"duration":420},"2750050":{"to":308,"transport":1,"price":64,"duration":95},"2750067":{"to":309,"transport":1,"price":81,"duration":120},"2750386":{"to":310,"transport":1,"price":32,"duration":330},"2750169":{"to":311,"transport":1,"price":68,"duration":410},"2750338":{"to":314,"transport":1,"price":17,"duration":310},"2750093":{"to":316,"transport":1,"price":85,"duration":105},"2750211":{"to":317,"transport":1,"price":80,"duration":475},"2750171":{"to":318,"transport":1,"price":25,"duration":335},"2750302":{"to":320,"transport":1,"price":55,"duration":305},"2750273":{"to":321,"transport":1,"price":85,"duration":250},"2750416":{"to":323,"transport":1,"price":23,"duration":380},"2750380":{"to":325,"transport":1,"price":61,"duration":375},"2750233":{"to":326,"transport":1,"price":130,"duration":110},"2750142":{"to":327,"transport":1,"price":65,"duration":220},"2750114":{"to":329,"transport":1,"price":53,"duration":190},"2750267":{"to":330,"transport":1,"price":77,"duration":225},"2750344":{"to":331,"transport":1,"price":36,"duration":270},"2750383":{"to":332,"transport":1,"price":42,"duration":400},"2750061":{"to":334,"transport":1,"price":40,"duration":195},"2750134":{"to":335,"transport":1,"price":49,"duration":75},"2750117":{"to":336,"transport":1,"price":59,"duration":300},"2750207":{"to":337,"transport":1,"price":35,"duration":555},"2750409":{"to":338,"transport":1,"price":18,"duration":250},"2750403":{"to":339,"transport":1,"price":70,"duration":440},"2750421":{"to":340,"transport":1,"price":90,"duration":375},"2750206":{"to":341,"transport":1,"price":30,"duration":335},"2750275":{"to":342,"transport":1,"price":60,"duration":90},"2750052":{"to":345,"transport":1,"price":118,"duration":335},"2750330":{"to":347,"transport":1,"price":97,"duration":415},"2750237":{"to":348,"transport":1,"price":74,"duration":105},"2750255":{"to":349,"transport":1,"price":26,"duration":455},"2750325":{"to":351,"transport":1,"price":75,"duration":105},"2750159":{"to":352,"transport":1,"price":49,"duration":260},"2750119":{"to":353,"transport":1,"price":27,"duration":65},"2750062":{"to":354,"transport":1,"price":40,"duration":70},"2750029":{"to":356,"transport":1,"price":86,"duration":365},"2750109":{"to":357,"transport":1,"price":21,"duration":270},"2750404":{"to":358,"transport":1,"price":25,"duration":815},"2750115":{"to":359,"transport":1,"price":106,"duration":480},"2750393":{"to":362,"transport":1,"price":130,"duration":335},"2750228":{"to":364,"transport":1,"price":67,"duration":145},"2750179":{"to":365,"transport":1,"price":115,"duration":305},"2750268":{"to":367,"transport":1,"price":26,"duration":480},"2750118":{"to":368,"transport":1,"price":14,"duration":215},"2750385":{"to":369,"transport":1,"price":22,"duration":240},"2750299":{"to":370,"transport":1,"price":97,"duration":90},"2750110":{"to":371,"transport":1,"price":27,"duration":355},"2750349":{"to":546,"transport":1,"price":50,"duration":450},"2750306":{"to":547,"transport":1,"price":270,"duration":1000},"2750243":{"to":548,"transport":1,"price":326,"duration":905},"2750019":{"to":550,"transport":1,"price":298,"duration":1000},"2750314":{"to":551,"transport":1,"price":420,"duration":1490},"2750248":{"to":552,"transport":1,"price":232,"duration":820},"2750276":{"to":553,"transport":1,"price":210,"duration":1165},"2750204":{"to":554,"transport":1,"price":199,"duration":905},"2750357":{"to":626,"transport":1,"price":122,"duration":795},"2750220":{"to":663,"transport":1,"price":217,"duration":740}}