{"280244":{"to":8,"transport":1,"price":208,"duration":70},"280117":{"to":9,"transport":1,"price":208,"duration":430},"280204":{"to":10,"transport":1,"price":262,"duration":750},"280246":{"to":11,"transport":1,"price":344,"duration":765},"280290":{"to":13,"transport":1,"price":217,"duration":290},"280304":{"to":14,"transport":1,"price":195,"duration":810},"280119":{"to":15,"transport":1,"price":335,"duration":485},"280158":{"to":17,"transport":1,"price":106,"duration":280},"280030":{"to":18,"transport":1,"price":253,"duration":500},"280212":{"to":20,"transport":1,"price":136,"duration":420},"280363":{"to":21,"transport":1,"price":217,"duration":435},"280047":{"to":22,"transport":1,"price":172,"duration":120},"280211":{"to":23,"transport":1,"price":246,"duration":500},"280159":{"to":24,"transport":1,"price":309,"duration":475},"280252":{"to":25,"transport":1,"price":226,"duration":440},"280349":{"to":26,"transport":1,"price":118,"duration":90},"280340":{"to":27,"transport":1,"price":371,"duration":855},"280303":{"to":29,"transport":1,"price":298,"duration":520},"280342":{"to":30,"transport":1,"price":389,"duration":390},"280147":{"to":31,"transport":2,"price":54,"duration":960},"280176":{"to":31,"transport":1,"price":145,"duration":100},"280351":{"to":32,"transport":1,"price":241,"duration":275},"280267":{"to":33,"transport":1,"price":118,"duration":435},"280062":{"to":34,"transport":1,"price":226,"duration":425},"280167":{"to":35,"transport":1,"price":172,"duration":115},"280171":{"to":36,"transport":1,"price":633,"duration":1315},"280135":{"to":37,"transport":1,"price":491,"duration":1145},"280262":{"to":38,"transport":1,"price":497,"duration":1130},"280313":{"to":39,"transport":1,"price":452,"duration":1267},"280274":{"to":40,"transport":1,"price":452,"duration":1165},"280264":{"to":41,"transport":1,"price":497,"duration":1170},"280395":{"to":42,"transport":1,"price":407,"duration":905},"280283":{"to":43,"transport":1,"price":349,"duration":715},"280350":{"to":44,"transport":1,"price":145,"duration":300},"280148":{"to":45,"transport":1,"price":157,"duration":305},"280301":{"to":48,"transport":1,"price":405,"duration":900},"280353":{"to":51,"transport":1,"price":438,"duration":1145},"280282":{"to":55,"transport":1,"price":243,"duration":615},"280374":{"to":56,"transport":1,"price":110,"duration":475},"280391":{"to":57,"transport":1,"price":199,"duration":450},"280146":{"to":58,"transport":1,"price":184,"duration":295},"280114":{"to":59,"transport":1,"price":420,"duration":715},"280103":{"to":61,"transport":1,"price":407,"duration":950},"280377":{"to":62,"transport":1,"price":535,"duration":1165},"280389":{"to":63,"transport":1,"price":434,"duration":945},"280208":{"to":64,"transport":1,"price":539,"duration":1235},"280165":{"to":65,"transport":1,"price":493,"duration":1310},"280116":{"to":66,"transport":1,"price":199,"duration":445},"280269":{"to":67,"transport":1,"price":501,"duration":745},"280332":{"to":68,"transport":1,"price":373,"duration":1340},"280198":{"to":69,"transport":1,"price":66,"duration":140},"280285":{"to":70,"transport":1,"price":1731,"duration":1350},"280293":{"to":71,"transport":1,"price":358,"duration":815},"280404":{"to":72,"transport":1,"price":667,"duration":1175},"280202":{"to":73,"transport":1,"price":546,"duration":2015},"280265":{"to":74,"transport":1,"price":304,"duration":635},"280169":{"to":75,"transport":1,"price":408,"duration":790},"280365":{"to":76,"transport":1,"price":393,"duration":760},"280166":{"to":77,"transport":1,"price":344,"duration":705},"280392":{"to":78,"transport":1,"price":181,"duration":155},"280251":{"to":79,"transport":1,"price":441,"duration":845},"280001":{"to":80,"transport":1,"price":423,"duration":835},"280172":{"to":81,"transport":1,"price":380,"duration":670},"280253":{"to":82,"transport":1,"price":433,"duration":800},"280002":{"to":83,"transport":1,"price":373,"duration":755},"280178":{"to":84,"transport":1,"price":241,"duration":455},"280104":{"to":85,"transport":1,"price":367,"duration":750},"280177":{"to":86,"transport":1,"price":205,"duration":310},"280329":{"to":87,"transport":1,"price":398,"duration":890},"280032":{"to":88,"transport":1,"price":395,"duration":765},"280354":{"to":89,"transport":1,"price":438,"duration":950},"280266":{"to":90,"transport":1,"price":395,"duration":675},"280268":{"to":91,"transport":1,"price":144,"duration":375},"280237":{"to":92,"transport":1,"price":328,"duration":650},"280373":{"to":93,"transport":1,"price":133,"duration":400},"280255":{"to":94,"transport":1,"price":408,"duration":655},"280199":{"to":95,"transport":1,"price":135,"duration":130},"280250":{"to":96,"transport":1,"price":373,"duration":690},"280369":{"to":98,"transport":1,"price":233,"duration":585},"280105":{"to":99,"transport":1,"price":341,"duration":715},"280050":{"to":101,"transport":1,"price":158,"duration":640},"280398":{"to":103,"transport":1,"price":120,"duration":485},"280081":{"to":104,"transport":1,"price":95,"duration":295},"280193":{"to":105,"transport":1,"price":90,"duration":635},"280196":{"to":106,"transport":1,"price":240,"duration":685},"280140":{"to":107,"transport":1,"price":148,"duration":550},"280065":{"to":108,"transport":1,"price":161,"duration":570},"280058":{"to":109,"transport":1,"price":220,"duration":520},"280088":{"to":111,"transport":1,"price":147,"duration":460},"280259":{"to":112,"transport":1,"price":163,"duration":380},"280409":{"to":113,"transport":1,"price":65,"duration":295},"280258":{"to":114,"transport":1,"price":107,"duration":155},"280347":{"to":115,"transport":1,"price":55,"duration":570},"280095":{"to":116,"transport":1,"price":135,"duration":465},"280310":{"to":118,"transport":1,"price":50,"duration":595},"280061":{"to":119,"transport":1,"price":147,"duration":640},"280385":{"to":120,"transport":1,"price":233,"duration":525},"280173":{"to":121,"transport":1,"price":73,"duration":755},"280384":{"to":122,"transport":1,"price":221,"duration":640},"280052":{"to":123,"transport":1,"price":118,"duration":360},"280142":{"to":124,"transport":1,"price":120,"duration":420},"280014":{"to":126,"transport":1,"price":220,"duration":440},"280133":{"to":127,"transport":1,"price":295,"duration":520},"280044":{"to":128,"transport":1,"price":150,"duration":465},"280035":{"to":129,"transport":1,"price":210,"duration":620},"280277":{"to":130,"transport":1,"price":54,"duration":460},"280141":{"to":131,"transport":1,"price":180,"duration":580},"280276":{"to":132,"transport":1,"price":206,"duration":710},"280006":{"to":134,"transport":1,"price":145,"duration":345},"280331":{"to":135,"transport":1,"price":102,"duration":375},"280284":{"to":136,"transport":1,"price":50,"duration":640},"280316":{"to":137,"transport":1,"price":200,"duration":530},"280294":{"to":140,"transport":1,"price":135,"duration":460},"280386":{"to":142,"transport":1,"price":270,"duration":655},"280094":{"to":145,"transport":1,"price":135,"duration":430},"280080":{"to":146,"transport":1,"price":170,"duration":435},"280064":{"to":147,"transport":1,"price":134,"duration":445},"280125":{"to":150,"transport":1,"price":200,"duration":645},"280048":{"to":151,"transport":1,"price":85,"duration":560},"280402":{"to":152,"transport":1,"price":172,"duration":380},"280339":{"to":153,"transport":1,"price":145,"duration":410},"280335":{"to":154,"transport":1,"price":240,"duration":625},"280328":{"to":160,"transport":1,"price":135,"duration":615},"280013":{"to":161,"transport":1,"price":130,"duration":460},"280059":{"to":162,"transport":1,"price":221,"duration":585},"280305":{"to":163,"transport":1,"price":120,"duration":270},"280209":{"to":164,"transport":1,"price":157,"duration":380},"280051":{"to":166,"transport":1,"price":215,"duration":620},"280348":{"to":171,"transport":1,"price":161,"duration":495},"280090":{"to":172,"transport":1,"price":147,"duration":580},"280018":{"to":174,"transport":1,"price":120,"duration":435},"280346":{"to":175,"transport":1,"price":180,"duration":665},"280232":{"to":176,"transport":1,"price":180,"duration":815},"280235":{"to":177,"transport":1,"price":170,"duration":610},"280180":{"to":178,"transport":1,"price":180,"duration":735},"280319":{"to":179,"transport":1,"price":95,"duration":675},"280093":{"to":180,"transport":1,"price":110,"duration":805},"280183":{"to":181,"transport":1,"price":150,"duration":685},"280324":{"to":183,"transport":1,"price":172,"duration":720},"280223":{"to":184,"transport":1,"price":113,"duration":615},"280161":{"to":186,"transport":1,"price":190,"duration":685},"280066":{"to":189,"transport":1,"price":150,"duration":575},"280249":{"to":191,"transport":1,"price":181,"duration":620},"280069":{"to":192,"transport":1,"price":140,"duration":455},"280367":{"to":193,"transport":1,"price":172,"duration":485},"280227":{"to":194,"transport":1,"price":339,"duration":660},"280257":{"to":196,"transport":1,"price":134,"duration":465},"280016":{"to":197,"transport":1,"price":130,"duration":435},"280156":{"to":200,"transport":1,"price":160,"duration":440},"280205":{"to":201,"transport":1,"price":123,"duration":530},"280358":{"to":202,"transport":1,"price":180,"duration":640},"280222":{"to":203,"transport":1,"price":170,"duration":640},"280271":{"to":204,"transport":1,"price":59,"duration":630},"280288":{"to":205,"transport":1,"price":65,"duration":590},"280226":{"to":206,"transport":1,"price":112,"duration":315},"280281":{"to":207,"transport":1,"price":84,"duration":175},"280225":{"to":209,"transport":1,"price":170,"duration":595},"280241":{"to":212,"transport":1,"price":68,"duration":725},"280099":{"to":213,"transport":1,"price":149,"duration":460},"280008":{"to":214,"transport":1,"price":187,"duration":550},"280217":{"to":215,"transport":1,"price":70,"duration":640},"280323":{"to":218,"transport":1,"price":170,"duration":940},"280338":{"to":219,"transport":1,"price":270,"duration":680},"280179":{"to":222,"transport":1,"price":237,"duration":720},"280228":{"to":224,"transport":1,"price":124,"duration":655},"280194":{"to":225,"transport":1,"price":96,"duration":680},"280213":{"to":227,"transport":1,"price":100,"duration":740},"280028":{"to":228,"transport":1,"price":240,"duration":740},"280345":{"to":230,"transport":1,"price":250,"duration":690},"280025":{"to":231,"transport":1,"price":160,"duration":225},"280300":{"to":233,"transport":1,"price":180,"duration":530},"280233":{"to":235,"transport":1,"price":260,"duration":530},"280106":{"to":236,"transport":1,"price":180,"duration":445},"280216":{"to":239,"transport":1,"price":170,"duration":620},"280070":{"to":240,"transport":1,"price":130,"duration":445},"280314":{"to":242,"transport":1,"price":159,"duration":625},"280387":{"to":243,"transport":1,"price":184,"duration":500},"280136":{"to":245,"transport":1,"price":180,"duration":600},"280273":{"to":246,"transport":1,"price":260,"duration":650},"280053":{"to":247,"transport":1,"price":120,"duration":410},"280033":{"to":248,"transport":1,"price":150,"duration":505},"280092":{"to":249,"transport":1,"price":240,"duration":530},"280297":{"to":250,"transport":1,"price":120,"duration":670},"280376":{"to":251,"transport":1,"price":270,"duration":760},"280120":{"to":252,"transport":1,"price":173,"duration":455},"280215":{"to":253,"transport":1,"price":210,"duration":440},"280306":{"to":257,"transport":1,"price":120,"duration":330},"280109":{"to":259,"transport":1,"price":140,"duration":415},"280394":{"to":261,"transport":1,"price":200,"duration":665},"280214":{"to":263,"transport":1,"price":328,"duration":645},"280230":{"to":264,"transport":1,"price":124,"duration":640},"280380":{"to":265,"transport":1,"price":270,"duration":705},"280055":{"to":266,"transport":1,"price":200,"duration":475},"280075":{"to":267,"transport":1,"price":180,"duration":385},"280236":{"to":268,"transport":1,"price":208,"duration":465},"280333":{"to":269,"transport":1,"price":160,"duration":555},"280068":{"to":270,"transport":1,"price":190,"duration":440},"280298":{"to":274,"transport":1,"price":140,"duration":680},"280049":{"to":275,"transport":1,"price":160,"duration":635},"280366":{"to":277,"transport":1,"price":147,"duration":525},"280102":{"to":279,"transport":1,"price":145,"duration":525},"280343":{"to":280,"transport":1,"price":123,"duration":485},"280110":{"to":282,"transport":1,"price":170,"duration":605},"280027":{"to":284,"transport":1,"price":70,"duration":580},"280401":{"to":285,"transport":1,"price":172,"duration":460},"280144":{"to":286,"transport":1,"price":65,"duration":655},"280286":{"to":287,"transport":1,"price":280,"duration":565},"280372":{"to":288,"transport":1,"price":200,"duration":465},"280248":{"to":289,"transport":1,"price":208,"duration":595},"280355":{"to":290,"transport":1,"price":360,"duration":795},"280034":{"to":291,"transport":1,"price":260,"duration":585},"280334":{"to":293,"transport":1,"price":147,"duration":475},"280023":{"to":294,"transport":1,"price":209,"duration":545},"280164":{"to":295,"transport":1,"price":180,"duration":385},"280097":{"to":297,"transport":1,"price":68,"duration":410},"280307":{"to":299,"transport":1,"price":130,"duration":455},"280185":{"to":300,"transport":1,"price":253,"duration":1125},"280229":{"to":302,"transport":1,"price":327,"duration":540},"280145":{"to":303,"transport":1,"price":55,"duration":615},"280364":{"to":304,"transport":1,"price":130,"duration":645},"280203":{"to":305,"transport":1,"price":160,"duration":445},"280071":{"to":306,"transport":1,"price":250,"duration":710},"280138":{"to":307,"transport":1,"price":177,"duration":735},"280056":{"to":308,"transport":1,"price":160,"duration":515},"280344":{"to":309,"transport":1,"price":123,"duration":320},"280322":{"to":310,"transport":1,"price":118,"duration":365},"280174":{"to":311,"transport":1,"price":226,"duration":670},"280189":{"to":314,"transport":1,"price":46,"duration":555},"280054":{"to":316,"transport":1,"price":130,"duration":470},"280292":{"to":317,"transport":1,"price":120,"duration":425},"280127":{"to":318,"transport":1,"price":75,"duration":680},"280245":{"to":320,"transport":1,"price":160,"duration":665},"280160":{"to":321,"transport":1,"price":80,"duration":625},"280085":{"to":323,"transport":1,"price":99,"duration":335},"280318":{"to":325,"transport":1,"price":180,"duration":580},"280186":{"to":326,"transport":1,"price":320,"duration":660},"280221":{"to":327,"transport":1,"price":172,"duration":615},"280113":{"to":329,"transport":1,"price":79,"duration":640},"280084":{"to":330,"transport":1,"price":118,"duration":360},"280087":{"to":331,"transport":1,"price":163,"duration":320},"280296":{"to":332,"transport":1,"price":160,"duration":825},"280021":{"to":334,"transport":1,"price":196,"duration":645},"280181":{"to":335,"transport":1,"price":160,"duration":585},"280007":{"to":336,"transport":1,"price":173,"duration":230},"280242":{"to":337,"transport":1,"price":310,"duration":900},"280309":{"to":338,"transport":1,"price":154,"duration":610},"280170":{"to":339,"transport":1,"price":89,"duration":290},"280326":{"to":340,"transport":1,"price":220,"duration":695},"280256":{"to":341,"transport":1,"price":110,"duration":710},"280317":{"to":342,"transport":1,"price":190,"duration":535},"280210":{"to":343,"transport":1,"price":209,"duration":530},"280206":{"to":345,"transport":1,"price":172,"duration":595},"280219":{"to":347,"transport":1,"price":184,"duration":640},"280220":{"to":348,"transport":1,"price":109,"duration":425},"280003":{"to":349,"transport":1,"price":145,"duration":350},"280192":{"to":351,"transport":1,"price":240,"duration":540},"280356":{"to":352,"transport":1,"price":230,"duration":640},"280278":{"to":353,"transport":1,"price":64,"duration":470},"280393":{"to":354,"transport":1,"price":120,"duration":605},"280118":{"to":356,"transport":1,"price":163,"duration":455},"280168":{"to":357,"transport":1,"price":41,"duration":365},"280403":{"to":359,"transport":1,"price":230,"duration":615},"280129":{"to":362,"transport":1,"price":295,"duration":620},"280010":{"to":364,"transport":1,"price":141,"duration":380},"280291":{"to":365,"transport":1,"price":43,"duration":555},"280330":{"to":367,"transport":1,"price":110,"duration":735},"280311":{"to":368,"transport":1,"price":154,"duration":440},"280357":{"to":369,"transport":1,"price":209,"duration":600},"280295":{"to":370,"transport":1,"price":123,"duration":425},"280175":{"to":371,"transport":1,"price":217,"duration":345},"280362":{"to":546,"transport":1,"price":109,"duration":365},"280289":{"to":547,"transport":1,"price":280,"duration":720},"280195":{"to":548,"transport":1,"price":434,"duration":1000},"280408":{"to":550,"transport":1,"price":246,"duration":785},"280375":{"to":551,"transport":1,"price":287,"duration":905},"280026":{"to":552,"transport":1,"price":177,"duration":415},"280407":{"to":553,"transport":1,"price":184,"duration":895},"280078":{"to":554,"transport":1,"price":166,"duration":680},"280388":{"to":626,"transport":1,"price":144,"duration":465},"280239":{"to":663,"transport":1,"price":398,"duration":965}}