{"730578":{"to":8,"transport":1,"price":633,"duration":1270},"730546":{"to":9,"transport":1,"price":452,"duration":1870},"730580":{"to":10,"transport":1,"price":353,"duration":1385},"730449":{"to":11,"transport":1,"price":270,"duration":645},"730509":{"to":13,"transport":1,"price":678,"duration":990},"730393":{"to":14,"transport":1,"price":195,"duration":495},"730455":{"to":15,"transport":1,"price":307,"duration":805},"730534":{"to":16,"transport":1,"price":433,"duration":905},"730488":{"to":17,"transport":1,"price":588,"duration":1050},"730571":{"to":18,"transport":1,"price":416,"duration":850},"730386":{"to":20,"transport":1,"price":633,"duration":1130},"730302":{"to":21,"transport":1,"price":678,"duration":1270},"730406":{"to":22,"transport":1,"price":588,"duration":865},"730549":{"to":23,"transport":1,"price":253,"duration":785},"730411":{"to":24,"transport":1,"price":309,"duration":645},"730335":{"to":25,"transport":1,"price":614,"duration":1375},"730424":{"to":26,"transport":1,"price":678,"duration":1205},"730430":{"to":27,"transport":1,"price":298,"duration":430},"730261":{"to":28,"transport":1,"price":769,"duration":1120},"730453":{"to":29,"transport":1,"price":678,"duration":1440},"730327":{"to":30,"transport":1,"price":1357,"duration":1080},"730379":{"to":31,"transport":1,"price":633,"duration":1095},"730349":{"to":32,"transport":1,"price":786,"duration":1010},"730500":{"to":33,"transport":1,"price":588,"duration":1195},"730458":{"to":34,"transport":1,"price":633,"duration":1070},"730305":{"to":35,"transport":1,"price":769,"duration":1230},"730037":{"to":36,"transport":1,"price":317,"duration":610},"730054":{"to":37,"transport":1,"price":442,"duration":870},"730156":{"to":38,"transport":1,"price":859,"duration":1214},"730012":{"to":39,"transport":1,"price":497,"duration":1020},"730013":{"to":40,"transport":1,"price":380,"duration":855},"730155":{"to":41,"transport":1,"price":678,"duration":1245},"730334":{"to":42,"transport":1,"price":633,"duration":1229},"730581":{"to":43,"transport":1,"price":498,"duration":980},"730242":{"to":44,"transport":1,"price":506,"duration":1065},"730241":{"to":45,"transport":1,"price":530,"duration":1030},"730539":{"to":48,"transport":1,"price":216,"duration":820},"730200":{"to":51,"transport":1,"price":330,"duration":735},"730114":{"to":53,"transport":1,"price":469,"duration":625},"730528":{"to":55,"transport":1,"price":387,"duration":765},"730324":{"to":56,"transport":1,"price":376,"duration":1015},"730330":{"to":57,"transport":1,"price":276,"duration":760},"730119":{"to":58,"transport":1,"price":663,"duration":1300},"730213":{"to":59,"transport":1,"price":393,"duration":825},"730051":{"to":60,"transport":1,"price":656,"duration":870},"730474":{"to":61,"transport":1,"price":643,"duration":870},"730567":{"to":62,"transport":1,"price":601,"duration":1114},"730026":{"to":63,"transport":1,"price":601,"duration":1364},"730260":{"to":64,"transport":1,"price":754,"duration":1975},"730100":{"to":65,"transport":1,"price":903,"duration":1075},"730329":{"to":66,"transport":1,"price":276,"duration":775},"730392":{"to":67,"transport":1,"price":343,"duration":735},"730456":{"to":68,"transport":1,"price":271,"duration":1020},"730214":{"to":69,"transport":1,"price":443,"duration":830},"730142":{"to":70,"transport":1,"price":106,"duration":210},"730224":{"to":71,"transport":1,"price":130,"duration":685},"730514":{"to":72,"transport":2,"price":36,"duration":615},"730513":{"to":72,"transport":3,"price":45,"duration":677},"730512":{"to":72,"transport":1,"price":52,"duration":85},"730420":{"to":74,"transport":1,"price":582,"duration":1600},"730515":{"to":75,"transport":1,"price":204,"duration":625},"730158":{"to":76,"transport":1,"price":224,"duration":425},"730357":{"to":77,"transport":1,"price":145,"duration":585},"730377":{"to":78,"transport":1,"price":633,"duration":1200},"730113":{"to":79,"transport":1,"price":183,"duration":625},"730524":{"to":80,"transport":1,"price":169,"duration":350},"730450":{"to":81,"transport":1,"price":135,"duration":490},"730352":{"to":82,"transport":1,"price":485,"duration":640},"730403":{"to":83,"transport":1,"price":265,"duration":765},"730280":{"to":84,"transport":1,"price":627,"duration":1075},"730047":{"to":85,"transport":1,"price":223,"duration":585},"730281":{"to":86,"transport":1,"price":482,"duration":1105},"730384":{"to":87,"transport":1,"price":344,"duration":570},"730250":{"to":88,"transport":1,"price":250,"duration":955},"730202":{"to":89,"transport":1,"price":223,"duration":810},"730391":{"to":90,"transport":1,"price":158,"duration":530},"730120":{"to":91,"transport":1,"price":331,"duration":870},"730050":{"to":92,"transport":1,"price":538,"duration":720},"730325":{"to":93,"transport":1,"price":320,"duration":760},"730024":{"to":94,"transport":1,"price":143,"duration":510},"730510":{"to":95,"transport":1,"price":389,"duration":840},"730025":{"to":96,"transport":1,"price":163,"duration":460},"730049":{"to":97,"transport":1,"price":249,"duration":760},"730249":{"to":98,"transport":1,"price":198,"duration":550},"730048":{"to":99,"transport":1,"price":262,"duration":545},"730093":{"to":101,"transport":1,"price":678,"duration":1535},"730498":{"to":103,"transport":1,"price":430,"duration":1510},"730444":{"to":104,"transport":1,"price":418,"duration":1325},"730409":{"to":105,"transport":1,"price":750,"duration":1530},"730323":{"to":106,"transport":1,"price":1000,"duration":1705},"730447":{"to":107,"transport":1,"price":662,"duration":1510},"730312":{"to":108,"transport":1,"price":738,"duration":1520},"730041":{"to":109,"transport":1,"price":850,"duration":1610},"730146":{"to":111,"transport":1,"price":540,"duration":1350},"730538":{"to":112,"transport":1,"price":746,"duration":1400},"730421":{"to":113,"transport":1,"price":559,"duration":1205},"730437":{"to":114,"transport":1,"price":746,"duration":1270},"730209":{"to":115,"transport":1,"price":714,"duration":1565},"730150":{"to":116,"transport":1,"price":393,"duration":1565},"730286":{"to":117,"transport":1,"price":1085,"duration":1420},"730230":{"to":118,"transport":1,"price":678,"duration":1655},"730196":{"to":119,"transport":1,"price":600,"duration":1515},"730126":{"to":120,"transport":1,"price":678,"duration":1410},"730558":{"to":121,"transport":1,"price":835,"duration":1635},"730122":{"to":122,"transport":1,"price":622,"duration":1540},"730016":{"to":123,"transport":1,"price":633,"duration":1405},"730129":{"to":124,"transport":1,"price":500,"duration":1330},"730292":{"to":126,"transport":1,"price":800,"duration":1475},"730293":{"to":127,"transport":1,"price":1000,"duration":1520},"730087":{"to":128,"transport":1,"price":500,"duration":1375},"730398":{"to":129,"transport":1,"price":639,"duration":1535},"730270":{"to":130,"transport":1,"price":540,"duration":1480},"730253":{"to":131,"transport":1,"price":730,"duration":1535},"730290":{"to":132,"transport":1,"price":859,"duration":1600},"730015":{"to":134,"transport":1,"price":588,"duration":1365},"730063":{"to":135,"transport":1,"price":655,"duration":1425},"730368":{"to":136,"transport":1,"price":700,"duration":1610},"730381":{"to":137,"transport":1,"price":600,"duration":1480},"730177":{"to":140,"transport":1,"price":612,"duration":1480},"730125":{"to":142,"transport":1,"price":848,"duration":1575},"730074":{"to":145,"transport":1,"price":650,"duration":1430},"730375":{"to":146,"transport":1,"price":1000,"duration":1470},"730294":{"to":147,"transport":1,"price":600,"duration":1390},"730195":{"to":150,"transport":1,"price":750,"duration":1535},"730301":{"to":151,"transport":1,"price":1000,"duration":1415},"730364":{"to":152,"transport":1,"price":600,"duration":1375},"730014":{"to":153,"transport":1,"price":588,"duration":1410},"730407":{"to":154,"transport":1,"price":950,"duration":1485},"730075":{"to":159,"transport":1,"price":700,"duration":1505},"730495":{"to":160,"transport":1,"price":600,"duration":1480},"730069":{"to":161,"transport":1,"price":550,"duration":1320},"730194":{"to":162,"transport":1,"price":500,"duration":1410},"730435":{"to":163,"transport":1,"price":839,"duration":1365},"730508":{"to":164,"transport":1,"price":452,"duration":1380},"730094":{"to":166,"transport":1,"price":622,"duration":1465},"730121":{"to":167,"transport":1,"price":961,"duration":1580},"730205":{"to":171,"transport":1,"price":644,"duration":1330},"730151":{"to":172,"transport":1,"price":737,"duration":1500},"730065":{"to":174,"transport":1,"price":500,"duration":1355},"730136":{"to":175,"transport":1,"price":850,"duration":1470},"730575":{"to":176,"transport":1,"price":1081,"duration":1680},"730044":{"to":177,"transport":1,"price":600,"duration":1440},"730256":{"to":178,"transport":1,"price":773,"duration":1575},"730476":{"to":179,"transport":1,"price":1100,"duration":1560},"730490":{"to":180,"transport":1,"price":750,"duration":1600},"730221":{"to":181,"transport":1,"price":700,"duration":1515},"730002":{"to":183,"transport":1,"price":678,"duration":1540},"730096":{"to":184,"transport":1,"price":622,"duration":1470},"730246":{"to":186,"transport":1,"price":900,"duration":1595},"730298":{"to":187,"transport":1,"price":1400,"duration":1620},"730387":{"to":189,"transport":1,"price":800,"duration":1590},"730389":{"to":191,"transport":1,"price":588,"duration":1570},"730188":{"to":192,"transport":1,"price":688,"duration":1350},"730531":{"to":193,"transport":1,"price":601,"duration":1510},"730285":{"to":194,"transport":1,"price":1074,"duration":1500},"730310":{"to":196,"transport":1,"price":589,"duration":1370},"730380":{"to":197,"transport":1,"price":650,"duration":1425},"730448":{"to":200,"transport":1,"price":500,"duration":1465},"730109":{"to":201,"transport":1,"price":639,"duration":1385},"730072":{"to":202,"transport":1,"price":900,"duration":1455},"730095":{"to":203,"transport":1,"price":735,"duration":1555},"730459":{"to":204,"transport":1,"price":771,"duration":1475},"730277":{"to":205,"transport":1,"price":800,"duration":1525},"730438":{"to":206,"transport":1,"price":839,"duration":1365},"730422":{"to":207,"transport":1,"price":513,"duration":1190},"730020":{"to":209,"transport":1,"price":600,"duration":1570},"730070":{"to":210,"transport":1,"price":800,"duration":1590},"730440":{"to":212,"transport":1,"price":904,"duration":1600},"730542":{"to":213,"transport":1,"price":550,"duration":1460},"730080":{"to":214,"transport":1,"price":682,"duration":1390},"730336":{"to":215,"transport":1,"price":650,"duration":1620},"730143":{"to":218,"transport":1,"price":800,"duration":1750},"730402":{"to":219,"transport":1,"price":900,"duration":1710},"730331":{"to":222,"transport":1,"price":565,"duration":1525},"730099":{"to":224,"transport":1,"price":791,"duration":1540},"730555":{"to":225,"transport":1,"price":491,"duration":1345},"730576":{"to":227,"transport":1,"price":1056,"duration":1695},"730572":{"to":228,"transport":1,"price":884,"duration":1675},"730401":{"to":230,"transport":1,"price":900,"duration":1550},"730548":{"to":231,"transport":1,"price":650,"duration":1240},"730086":{"to":233,"transport":1,"price":650,"duration":1420},"730248":{"to":235,"transport":1,"price":600,"duration":1405},"730233":{"to":236,"transport":1,"price":543,"duration":1430},"730084":{"to":239,"transport":1,"price":490,"duration":1660},"730187":{"to":240,"transport":1,"price":639,"duration":1460},"730487":{"to":242,"transport":1,"price":795,"duration":1555},"730559":{"to":243,"transport":1,"price":589,"duration":1405},"730433":{"to":244,"transport":1,"price":950,"duration":2265},"730135":{"to":245,"transport":1,"price":650,"duration":1655},"730127":{"to":246,"transport":1,"price":900,"duration":1470},"730067":{"to":247,"transport":1,"price":550,"duration":1310},"730247":{"to":248,"transport":1,"price":550,"duration":1475},"730400":{"to":249,"transport":1,"price":565,"duration":1560},"730278":{"to":250,"transport":1,"price":825,"duration":1560},"730429":{"to":251,"transport":1,"price":950,"duration":1710},"730046":{"to":252,"transport":1,"price":500,"duration":1330},"730431":{"to":253,"transport":1,"price":500,"duration":1455},"730341":{"to":257,"transport":1,"price":884,"duration":1360},"730297":{"to":259,"transport":1,"price":650,"duration":1470},"730295":{"to":261,"transport":1,"price":850,"duration":1525},"730309":{"to":262,"transport":1,"price":786,"duration":1550},"730410":{"to":263,"transport":1,"price":1074,"duration":1555},"730570":{"to":264,"transport":1,"price":835,"duration":1460},"730326":{"to":265,"transport":1,"price":1130,"duration":1565},"730413":{"to":266,"transport":1,"price":737,"duration":1430},"730522":{"to":267,"transport":1,"price":393,"duration":1390},"730089":{"to":268,"transport":1,"price":995,"duration":1410},"730219":{"to":269,"transport":1,"price":650,"duration":1505},"730064":{"to":270,"transport":1,"price":600,"duration":1455},"730003":{"to":273,"transport":1,"price":904,"duration":1845},"730345":{"to":274,"transport":1,"price":700,"duration":1545},"730520":{"to":275,"transport":1,"price":1028,"duration":1495},"730518":{"to":276,"transport":1,"price":1085,"duration":1650},"730255":{"to":277,"transport":1,"price":516,"duration":1415},"730485":{"to":279,"transport":1,"price":393,"duration":1570},"730496":{"to":280,"transport":1,"price":904,"duration":1570},"730128":{"to":282,"transport":1,"price":850,"duration":1525},"730276":{"to":284,"transport":1,"price":750,"duration":1510},"730365":{"to":285,"transport":1,"price":700,"duration":1460},"730525":{"to":286,"transport":1,"price":850,"duration":1720},"730045":{"to":287,"transport":1,"price":1000,"duration":1390},"730563":{"to":288,"transport":1,"price":737,"duration":1320},"730388":{"to":289,"transport":1,"price":904,"duration":1815},"730317":{"to":290,"transport":1,"price":850,"duration":1710},"730397":{"to":291,"transport":1,"price":589,"duration":1545},"730004":{"to":293,"transport":1,"price":434,"duration":1365},"730486":{"to":294,"transport":1,"price":851,"duration":1530},"730059":{"to":295,"transport":1,"price":785,"duration":1375},"730414":{"to":297,"transport":1,"price":614,"duration":1375},"730439":{"to":299,"transport":1,"price":513,"duration":1500},"730038":{"to":300,"transport":1,"price":723,"duration":1635},"730226":{"to":301,"transport":1,"price":2333,"duration":1620},"730470":{"to":302,"transport":1,"price":1309,"duration":1640},"730042":{"to":303,"transport":1,"price":500,"duration":1335},"730043":{"to":304,"transport":1,"price":800,"duration":1690},"730319":{"to":305,"transport":1,"price":588,"duration":1500},"730416":{"to":306,"transport":1,"price":958,"duration":1550},"730164":{"to":307,"transport":1,"price":883,"duration":1540},"730073":{"to":308,"transport":1,"price":900,"duration":1485},"730055":{"to":309,"transport":1,"price":543,"duration":1415},"730060":{"to":310,"transport":1,"price":720,"duration":1390},"730355":{"to":311,"transport":1,"price":904,"duration":1570},"730140":{"to":314,"transport":1,"price":540,"duration":1500},"730218":{"to":315,"transport":1,"price":450,"duration":1565},"730066":{"to":316,"transport":1,"price":650,"duration":1445},"730029":{"to":317,"transport":1,"price":490,"duration":1465},"730193":{"to":318,"transport":1,"price":750,"duration":1615},"730348":{"to":320,"transport":1,"price":750,"duration":1555},"730244":{"to":321,"transport":1,"price":600,"duration":1590},"730056":{"to":323,"transport":1,"price":633,"duration":1430},"730254":{"to":325,"transport":1,"price":730,"duration":1510},"730427":{"to":326,"transport":1,"price":1200,"duration":1560},"730541":{"to":327,"transport":1,"price":563,"duration":1510},"730532":{"to":329,"transport":1,"price":430,"duration":1380},"730061":{"to":330,"transport":1,"price":785,"duration":1430},"730210":{"to":331,"transport":1,"price":588,"duration":1375},"730478":{"to":332,"transport":1,"price":950,"duration":1760},"730471":{"to":334,"transport":1,"price":655,"duration":1500},"730454":{"to":335,"transport":1,"price":700,"duration":1525},"730206":{"to":336,"transport":1,"price":470,"duration":1130},"730321":{"to":337,"transport":1,"price":800,"duration":1715},"730304":{"to":338,"transport":1,"price":543,"duration":1550},"730223":{"to":339,"transport":1,"price":466,"duration":1355},"730110":{"to":340,"transport":1,"price":786,"duration":1605},"730034":{"to":341,"transport":1,"price":850,"duration":1635},"730296":{"to":342,"transport":1,"price":650,"duration":1490},"730101":{"to":343,"transport":1,"price":900,"duration":1490},"730112":{"to":345,"transport":1,"price":540,"duration":1470},"730358":{"to":347,"transport":1,"price":971,"duration":1545},"730234":{"to":348,"transport":1,"price":633,"duration":1325},"730090":{"to":349,"transport":1,"price":678,"duration":1385},"730408":{"to":351,"transport":1,"price":550,"duration":1515},"730346":{"to":352,"transport":1,"price":1100,"duration":1760},"730269":{"to":353,"transport":1,"price":491,"duration":1400},"730523":{"to":354,"transport":1,"price":850,"duration":1505},"730320":{"to":356,"transport":1,"price":588,"duration":1550},"730395":{"to":357,"transport":1,"price":543,"duration":1445},"730370":{"to":359,"transport":1,"price":1148,"duration":1595},"730291":{"to":362,"transport":1,"price":1300,"duration":1730},"730441":{"to":364,"transport":1,"price":588,"duration":1335},"730511":{"to":365,"transport":1,"price":554,"duration":1560},"730354":{"to":367,"transport":1,"price":1100,"duration":1730},"730231":{"to":368,"transport":1,"price":497,"duration":1420},"730540":{"to":369,"transport":1,"price":1047,"duration":1625},"730068":{"to":370,"transport":1,"price":500,"duration":1310},"730394":{"to":371,"transport":1,"price":588,"duration":1440},"730197":{"to":546,"transport":1,"price":723,"duration":1460},"730452":{"to":547,"transport":1,"price":380,"duration":1825},"730263":{"to":548,"transport":1,"price":497,"duration":1055},"730551":{"to":550,"transport":1,"price":416,"duration":930},"730475":{"to":551,"transport":1,"price":608,"duration":1215},"730252":{"to":552,"transport":1,"price":552,"duration":855},"730184":{"to":553,"transport":1,"price":298,"duration":1150},"730001":{"to":554,"transport":1,"price":387,"duration":1045},"730434":{"to":626,"transport":1,"price":254,"duration":835},"730052":{"to":663,"transport":1,"price":678,"duration":1160}}